knlp/__init__.py
knlp/application/__init__.py
knlp/application/wudao.py
knlp/common/__init__.py
knlp/common/constant.py
knlp/data/__init__.py
knlp/data/pytest_data.txt
knlp/data/stopwords.txt
knlp/data/seg_data/train/__init__.py
knlp/data/seg_data/train/pku_hmm_training_data_sample.txt
knlp/data/seg_data/train/pku_vocab.txt
knlp/information_extract/__init__.py
knlp/information_extract/inference.py
knlp/information_extract/keywords_extraction/README.md
knlp/information_extract/keywords_extraction/__init__.py
knlp/information_extract/keywords_extraction/label.txt
knlp/information_extract/keywords_extraction/seg4IE.py
knlp/information_extract/keywords_extraction/textrank.py
knlp/information_extract/keywords_extraction/textrank_keyword.py
knlp/information_extract/keywords_extraction/textrank_sentence.py
knlp/model/__init__.py
knlp/model/hmm/emission_pro.json
knlp/model/hmm/init_state_set.json
knlp/model/hmm/state_set.json
knlp/model/hmm/transition_pro.json
knlp/nn/__init__.py
knlp/nn/base_nn_model.py
knlp/passage_summary/__init__.py
knlp/passage_summary/inference.py
knlp/samples/IE_sample.py
knlp/samples/__init__.py
knlp/samples/hmm_sample.py
knlp/samples/seg_evaluation.py
knlp/samples/seg_sample.py
knlp/seq_generation/__init__.py
knlp/seq_generation/poem_gen/__init__.py
knlp/seq_generation/poem_gen/fast_api_wudao.py
knlp/seq_labeling/__init__.py
knlp/seq_labeling/data_helper.py
knlp/seq_labeling/inference.py
knlp/seq_labeling/ner.py
knlp/seq_labeling/seg.py
knlp/seq_labeling/utils.py
knlp/seq_labeling/crf/__init__.py
knlp/seq_labeling/crf/train.py
knlp/seq_labeling/hmm/__init__.py
knlp/seq_labeling/hmm/inference.py
knlp/seq_labeling/hmm/train.py
knlp/seq_labeling/model_train/__init__.py
knlp/seq_labeling/model_train/evaluation_seq_labeling.py
knlp/seq_labeling/model_train/train_base.py
knlp/seq_sentiment/__init__.py
knlp/seq_sentiment/inference.py
knlp/seq_sentiment/sentiment.py
knlp/similarity/__init__.py
knlp/similarity/inference.py
knlp-0.2.2.dist-info/LICENSE.md
knlp-0.2.2.dist-info/METADATA
knlp-0.2.2.dist-info/WHEEL
knlp-0.2.2.dist-info/top_level.txt
knlp-0.2.2.dist-info/RECORD
