Metadata-Version: 2.1
Name: knlp
Version: 0.2.2
Summary: KUAI SU(Quickly use) Python toolkit for Chinese Language Processing.
Home-page: https://github.com/DukeEnglish/knlp
Author: Junyi Li
Author-email: ljyduke@gmail.com
License: UNKNOWN
Platform: UNKNOWN
Classifier: Programming Language :: Python :: 3
Classifier: License :: OSI Approved :: MIT License
Classifier: Operating System :: OS Independent
Requires-Dist: asttokens (==2.0.2)
Requires-Dist: attrs (==20.3.0)
Requires-Dist: decorator (==4.4.2)
Requires-Dist: executing (==0.3.3)
Requires-Dist: heartrate (==0.2.1)
Requires-Dist: importlib-metadata (==3.4.0)
Requires-Dist: iniconfig (==1.1.1)
Requires-Dist: jieba (==0.42.1)
Requires-Dist: networkx (==2.5)
Requires-Dist: numpy (==1.19.5)
Requires-Dist: packaging (==20.9)
Requires-Dist: pluggy (==0.13.1)
Requires-Dist: py (==1.10.0)
Requires-Dist: pyparsing (==2.4.7)
Requires-Dist: snownlp (==0.12.3)
Requires-Dist: toml (==0.10.2)
Requires-Dist: typing-extensions (==3.7.4.3)
Requires-Dist: zipp (==3.4.0)
